README.md
setup.py
cleandev_validator/__init__.py
cleandev_validator/inmutables.py
cleandev_validator.egg-info/PKG-INFO
cleandev_validator.egg-info/SOURCES.txt
cleandev_validator.egg-info/dependency_links.txt
cleandev_validator.egg-info/requires.txt
cleandev_validator.egg-info/top_level.txt